{
  "project_info": {
    "project_number": "944951770952",
    "project_id": "final-cinechips",
    "storage_bucket": "final-cinechips.firebasestorage.app"
  },
  "client": [
    {
      "client_info": {
        "mobilesdk_app_id": "1:944951770952:android:09ddd6603e607e1ab07d7d",
        "android_client_info": {
          "package_name": "com.example.cinechips"
        }
      },
      "oauth_client": [],
      "api_key": [
        {
          "current_key": "AIzaSyBh6LQXvrIFJt2ryER0ZiVz8hCp7aDuu5o"
        }
      ],
      "services": {
        "appinvite_service": {
          "other_platform_oauth_client": []
        }
      }
    }
  ],
  "configuration_version": "1"
}